shippedbrain/__init__.py
shippedbrain/cli.py
shippedbrain/shippedbrain.py
tests/__init__.py
tests/conftest.py
tests/test_shipped_brain.py
tests/resources/__init__.py
tests/resources/train.py
shippedbrain-0.0.6.dist-info/LICENSE
shippedbrain-0.0.6.dist-info/METADATA
shippedbrain-0.0.6.dist-info/WHEEL
shippedbrain-0.0.6.dist-info/entry_points.txt
shippedbrain-0.0.6.dist-info/top_level.txt
shippedbrain-0.0.6.dist-info/RECORD
