Metadata-Version: 2.1
Name: shippedbrain
Version: 0.0.6
Summary: Client library to create serverless REST endpoints on shippedbrain.com
Home-page: https://github.com/shippedbrain/shippedbrain
Author: Shipped Brain
Author-email: info@shippedbrain.com
License: LICENSE
Keywords: pretrained-models,shipped-brain,machine-learning,artificial-intelligence,deploy,serve,serverless,model-hub,data-science,mlflow
Platform: UNKNOWN
Classifier: Intended Audience :: Developers
Classifier: Intended Audience :: Education
Classifier: Intended Audience :: Science/Research
Classifier: License :: OSI Approved :: Apache Software License
Classifier: Operating System :: OS Independent
Classifier: Programming Language :: Python :: 3
Classifier: Topic :: Scientific/Engineering :: Artificial Intelligence
Requires-Python: >=3.6.0
Requires-Dist: mlflow
Requires-Dist: click
Provides-Extra: dev
Requires-Dist: pytest ; extra == 'dev'
